catalogpy/__init__.py
catalogpy/catalog.py
catalogpy-1.5.dist-info/licenses/LICENSE
catalogpy-1.5.dist-info/METADATA
catalogpy-1.5.dist-info/WHEEL
catalogpy-1.5.dist-info/top_level.txt
catalogpy-1.5.dist-info/RECORD
