Metadata-Version: 2.4
Name: catalogpy
Version: 1.5
Summary: Libreria per ordinare testi stringhe e liste
Home-page: https://github.com/Gabinan890/catalogpy
Author: Gabriele Della Fazia Ristori
Author-email: gabriele.ristori.0110@gmail.com
Classifier: Programming Language :: Python :: 3
Classifier: License :: OSI Approved :: MIT License
Classifier: Operating System :: OS Independent
Requires-Python: >=3.8
License-File: LICENSE
Dynamic: author
Dynamic: author-email
Dynamic: classifier
Dynamic: description
Dynamic: description-content-type
Dynamic: home-page
Dynamic: license-file
Dynamic: requires-python
Dynamic: summary
